{
    "clusters": [
        {
            "x": 0.5235602094240838,
            "y": 0.2166175000284133,
            "z": 0.5167354561870744,
            "cluster": 0
        },
        {
            "x": 0.7155322862129145,
            "y": 0.0,
            "z": 0.31513192581038424,
            "cluster": 0
        },
        {
            "x": 0.3769633507853403,
            "y": 0.2166175000284133,
            "z": 0.49138703294334696,
            "cluster": 1
        },
        {
            "x": 0.0506108202443281,
            "y": 0.2166175000284133,
            "z": 0.4508528165875682,
            "cluster": 1
        },
        {
            "x": 0.6509598603839442,
            "y": 0.2166175000284133,
            "z": 0.48159478782398524,
            "cluster": 0
        },
        {
            "x": 0.5846422338568935,
            "y": 0.0,
            "z": 0.33450473123671876,
            "cluster": 0
        },
        {
            "x": 0.6893542757417103,
            "y": 0.0,
            "z": 0.2151105324389712,
            "cluster": 0
        },
        {
            "x": 0.3769633507853403,
            "y": 0.2166175000284133,
            "z": 0.25080968175093277,
            "cluster": 1
        },
        {
            "x": 0.0506108202443281,
            "y": 0.0,
            "z": 0.35725153336536314,
            "cluster": 1
        },
        {
            "x": 0.18150087260034903,
            "y": 0.2166175000284133,
            "z": 0.5312860607449695,
            "cluster": 1
        },
        {
            "x": 0.2670157068062827,
            "y": 0.0,
            "z": 0.40716042061573365,
            "cluster": 1
        },
        {
            "x": 0.631762652705061,
            "y": 0.0,
            "z": 0.11508948715935578,
            "cluster": 0
        },
        {
            "x": 1.0,
            "y": 0.0,
            "z": 0.31513192581038424,
            "cluster": 0
        },
        {
            "x": 0.9930191972076788,
            "y": 0.0,
            "z": 0.3603844609133449,
            "cluster": 0
        },
        {
            "x": 0.9912739965095986,
            "y": 0.0,
            "z": 0.35725153336536314,
            "cluster": 0
        },
        {
            "x": 0.08900523560209424,
            "y": 0.7406201244057928,
            "z": 0.6116277140700028,
            "cluster": 1
        },
        {
            "x": 0.9790575916230366,
            "y": 0.0,
            "z": 0.33379400918482577,
            "cluster": 0
        },
        {
            "x": 0.031413612565445025,
            "y": 1.0,
            "z": 1.0,
            "cluster": 1
        },
        {
            "x": 0.7172774869109948,
            "y": 0.0,
            "z": 0.31513192581038424,
            "cluster": 0
        },
        {
            "x": 0.7172774869109948,
            "y": 0.0,
            "z": 0.31513192581038424,
            "cluster": 0
        },
        {
            "x": 0.7120418848167539,
            "y": 0.0,
            "z": 0.07939055540387353,
            "cluster": 0
        },
        {
            "x": 0.7085514834205934,
            "y": 0.0,
            "z": 0.2151105324389712,
            "cluster": 0
        },
        {
            "x": 0.04013961605584642,
            "y": 0.3703100622028965,
            "z": 0.39916731400925054,
            "cluster": 1
        },
        {
            "x": 0.7050610820244329,
            "y": 0.0,
            "z": 0.381014453522225,
            "cluster": 0
        },
        {
            "x": 0.7033158813263525,
            "y": 0.0,
            "z": 0.40716042061573365,
            "cluster": 0
        },
        {
            "x": 0.7085514834205934,
            "y": 0.0,
            "z": 0.31513192581038424,
            "cluster": 0
        },
        {
            "x": 0.7050610820244329,
            "y": 0.0,
            "z": 0.4508528165875682,
            "cluster": 0
        },
        {
            "x": 0.699825479930192,
            "y": 0.0,
            "z": 0.26648231410874473,
            "cluster": 0
        },
        {
            "x": 0.041884816753926704,
            "y": 0.8598333372483921,
            "z": 0.8799879197433478,
            "cluster": 1
        },
        {
            "x": 0.6841186736474695,
            "y": 0.0,
            "z": 0.24529373057617954,
            "cluster": 0
        },
        {
            "x": 0.36649214659685864,
            "y": 0.2166175000284133,
            "z": 0.45163447044083677,
            "cluster": 1
        },
        {
            "x": 0.6527050610820244,
            "y": 0.0,
            "z": 0.31513192581038424,
            "cluster": 0
        },
        {
            "x": 0.6474694589877836,
            "y": 0.2166175000284133,
            "z": 0.3753385821014959,
            "cluster": 0
        },
        {
            "x": 0.5619546247818499,
            "y": 0.0,
            "z": 0.0,
            "cluster": 0
        },
        {
            "x": 0.059336823734729496,
            "y": 0.803545062259723,
            "z": 0.6671370139480254,
            "cluster": 1
        },
        {
            "x": 0.525305410122164,
            "y": 0.0,
            "z": 0.381014453522225,
            "cluster": 0
        },
        {
            "x": 0.525305410122164,
            "y": 0.0,
            "z": 0.38923120624053636,
            "cluster": 0
        },
        {
            "x": 0.525305410122164,
            "y": 0.0,
            "z": 0.38923120624053636,
            "cluster": 0
        },
        {
            "x": 0.225130890052356,
            "y": 0.3703100622028965,
            "z": 0.5653992127718174,
            "cluster": 1
        },
        {
            "x": 0.506108202443281,
            "y": 0.0,
            "z": 0.135719324370011,
            "cluster": 0
        },
        {
            "x": 0.4799301919720768,
            "y": 0.0,
            "z": 0.24529373057617954,
            "cluster": 0
        },
        {
            "x": 0.462478184991274,
            "y": 0.0,
            "z": 0.2945019580653777,
            "cluster": 0
        },
        {
            "x": 0.45200698080279234,
            "y": 0.0,
            "z": 0.40716042061573365,
            "cluster": 0
        },
        {
            "x": 0.06282722513089005,
            "y": 0.2166175000284133,
            "z": 0.4945452321397658,
            "cluster": 1
        },
        {
            "x": 0.3769633507853403,
            "y": 0.0,
            "z": 0.27143962774009944,
            "cluster": 0
        },
        {
            "x": 0.4328097731239092,
            "y": 0.0,
            "z": 0.33379400918482577,
            "cluster": 0
        },
        {
            "x": 0.418848167539267,
            "y": 0.0,
            "z": 0.09202732000173171,
            "cluster": 0
        },
        {
            "x": 0.3944153577661431,
            "y": 0.2166175000284133,
            "z": 0.41671372715336874,
            "cluster": 1
        },
        {
            "x": 0.3612565445026178,
            "y": 0.3703100622028965,
            "z": 0.15964985192682668,
            "cluster": 1
        },
        {
            "x": 0.35776614310645727,
            "y": 0.0,
            "z": 0.381014453522225,
            "cluster": 1
        },
        {
            "x": 0.35602094240837695,
            "y": 0.0,
            "z": 0.28898600067467406,
            "cluster": 1
        },
        {
            "x": 0.35602094240837695,
            "y": 0.0,
            "z": 0.28099291096785506,
            "cluster": 1
        },
        {
            "x": 0.33856893542757416,
            "y": 0.0,
            "z": 0.3455388464789153,
            "cluster": 1
        },
        {
            "x": 0.3368237347294939,
            "y": 0.0,
            "z": 0.3166921224392992,
            "cluster": 1
        },
        {
            "x": 0.2844677137870855,
            "y": 0.2166175000284133,
            "z": 0.43622164627001997,
            "cluster": 1
        },
        {
            "x": 0.5898778359511344,
            "y": 0.0,
            "z": 0.31513192581038424,
            "cluster": 0
        },
        {
            "x": 0.0034904013961605585,
            "y": 0.2166175000284133,
            "z": 0.49610543249826783,
            "cluster": 1
        },
        {
            "x": 0.2024432809773124,
            "y": 0.0,
            "z": 0.35725153336536314,
            "cluster": 1
        },
        {
            "x": 0.19720767888307156,
            "y": 0.0,
            "z": 0.18405519068885598,
            "cluster": 1
        },
        {
            "x": 0.193717277486911,
            "y": 0.0,
            "z": 0.381014453522225,
            "cluster": 1
        },
        {
            "x": 0.19022687609075042,
            "y": 0.0,
            "z": 0.10389774500515804,
            "cluster": 1
        },
        {
            "x": 0.15008726003490402,
            "y": 0.0,
            "z": 0.35725153336536314,
            "cluster": 1
        },
        {
            "x": 0.14659685863874344,
            "y": 0.0,
            "z": 0.03569871420166202,
            "cluster": 1
        },
        {
            "x": 0.14485165794066318,
            "y": 0.0,
            "z": 0.3603844609133449,
            "cluster": 1
        },
        {
            "x": 0.1343804537521815,
            "y": 0.0,
            "z": 0.28099291096785506,
            "cluster": 1
        },
        {
            "x": 0.14136125654450263,
            "y": 0.0,
            "z": 0.31513192581038424,
            "cluster": 1
        },
        {
            "x": 0.12914485165794065,
            "y": 0.2166175000284133,
            "z": 0.6773750010761211,
            "cluster": 1
        },
        {
            "x": 0.027923211169284468,
            "y": 0.2166175000284133,
            "z": 0.49233985284512716,
            "cluster": 1
        },
        {
            "x": 0.11518324607329843,
            "y": 0.2166175000284133,
            "z": 0.4258225306906122,
            "cluster": 1
        },
        {
            "x": 0.11169284467713787,
            "y": 0.0,
            "z": 0.3373220995082515,
            "cluster": 1
        },
        {
            "x": 0.06631762652705062,
            "y": 0.0,
            "z": 0.30713883144159637,
            "cluster": 1
        },
        {
            "x": 0.041884816753926704,
            "y": 0.0,
            "z": 0.36346804911932784,
            "cluster": 1
        },
        {
            "x": 0.02268760907504363,
            "y": 0.0,
            "z": 0.3913653296832505,
            "cluster": 1
        },
        {
            "x": 0.005235602094240838,
            "y": 0.0,
            "z": 0.04833543800811794,
            "cluster": 1
        },
        {
            "x": 0.0,
            "y": 0.0,
            "z": 0.36346804911932784,
            "cluster": 1
        }
    ],
    "centroids": [
        {
            "x": 0.6463915409095575,
            "y": 0.019113308826036467,
            "z": 0.302366033555717,
            "label": "Centroid 0"
        },
        {
            "x": 0.17145532711871622,
            "y": 0.17352045636252578,
            "z": 0.40152378205839895,
            "label": "Centroid 1"
        }
    ]
}